LabWeek2/simple_circuit3.v
module simple_circuit3 (A2,B2,C2,Z);  
output Z;
input A2, B2, C2;
wire W1, W2, W3;
and G1(W1, B2, C2);
or G2(W2, W1, A2);
and G3(W3, A2, B2);
or G4(Z, W2, W3);
endmodule

LabWeek2/tb_simple_circuit3.v
module tb_simple_circuit3;
reg A2, B2, C2;
wire Z;
simple_circuit3 c1(A2,B2,C2,Z);

initial
begin
#0 A2=0;B2=0;C2=0;
#5 A2=0;B2=0;C2=1;
#5 A2=0;B2=1;C2=0;
#5 A2=0;B2=1;C2=1;
#5 A2=1;B2=0;C2=0;
#5 A2=1;B2=0;C2=1;
#5 A2=1;B2=1;C2=0;
#5 A2=1;B2=1;C2=1;
#5;
end

initial
begin
$monitor($time, " A2=%b, B2=%b, C2=%b, Z=%b", A2, B2, C2, Z);   
end
initial
begin
$dumpfile ("simple_circuit3.vcd");
$dumpvars (0, c1);
end
endmodule

LabWeek2/simple_circuit3.vcd
$date
	Tue Aug 22 22:59:24 2023
$end
$version
	Icarus Verilog
$end
$timescale
	1s
$end
$scope module tb_simple_circuit3 $end
$scope module c1 $end
$var wire 1 ! A2 $end
$var wire 1 " B2 $end
$var wire 1 # C2 $end
$var wire 1 $ W1 $end
$var wire 1 % W2 $end
$var wire 1 & W3 $end
$var wire 1 ' Z $end
$upscope $end
$upscope $end
$enddefinitions $end
#0
$dumpvars
0'
0&
0%
0$
0#
0"
0!
$end
#5
1#
#10
0#
1"
#15
1'
1%
1$
1#
#20
0$
0#
0"
1!
#25
1#
#30
1&
0#
1"
#35
1$
1#
