LabWeek2/simple_circuit2.v
module simple_circuit2 (A,B,C,D);  
output D;
input A, B, C;
wire W1;
and G1(W1, B, C);
or G2(D, W1, A);
endmodule

LabWeek2/tb_simple_circuit2.v
module tb_simple_circuit2;
reg A, B, C;
wire D;
simple_circuit2 c1(A,B,C,D);

initial
begin
#0 A=0;B=0;C=0;
#5 A=0;B=0;C=1;
#5 A=0;B=1;C=0;
#5 A=0;B=1;C=1;
#5 A=1;B=0;C=0;
#5 A=1;B=0;C=1;
#5 A=1;B=1;C=0;
#5 A=1;B=1;C=1;
#5;
end

initial
begin
$monitor($time, " A=%b, B=%b, C=%b, D=%b", A, B, C, D);   
end
initial
begin
$dumpfile ("simple_circuit2.vcd");
$dumpvars (0, c1);
end
endmodule

LabWeek2/simple_circuit2.vcd
$date
	Tue Aug 22 22:49:49 2023
$end
$version
	Icarus Verilog
$end
$timescale
	1s
$end
$scope module tb_simple_circuit2 $end
$scope module c1 $end
$var wire 1 ! A $end
$var wire 1 " B $end
$var wire 1 # C $end
$var wire 1 $ D $end
$var wire 1 % W1 $end
$upscope $end
$upscope $end
$enddefinitions $end
#0
$dumpvars
0%
0$
0#
0"
0!
$end
#5
1#
#10
0#
1"
#15
1$
1%
1#
#20
0%
0#
0"
1!
#25
1#
#30
0#
1"
#35
1%
1#
