LabWeek2/simple_circuit.v
module simple_circuit (A,B,C,D,E);  
output D, E;
input A, B, C;
wire W1;
and G1(W1, A, B);
not G2(E, C);
or G3(D, W1, E);
endmodule

LabWeek2/tb_simple_circuit.v
module tb_simple_circuit;
reg A, B, C;
wire D, E;
simple_circuit c1(A,B,C,D,E);

initial
begin
#0 A=0;B=0;C=0;
#5 A=0;B=0;C=1;
#5 A=0;B=1;C=0;
#5 A=0;B=1;C=1;
#5 A=1;B=0;C=0;
#5 A=1;B=0;C=1;
#5 A=1;B=1;C=0;
#5 A=1;B=1;C=1;
#5;
end

initial
begin
$monitor($time, " A=%b, B=%b, C=%b, D=%b, E=%b", A, B, C, D, E);   
end
initial
begin
$dumpfile ("simple_circuit.vcd");
$dumpvars (0, c1);
end
endmodule

LabWeek2/simple_circuit.vcd
$date
	Tue Aug 22 22:40:02 2023
$end
$version
	Icarus Verilog
$end
$timescale
	1s
$end
$scope module tb_simple_circuit $end
$scope module c1 $end
$var wire 1 ! A $end
$var wire 1 " B $end
$var wire 1 # C $end
$var wire 1 $ D $end
$var wire 1 % E $end
$var wire 1 & W1 $end
$upscope $end
$upscope $end
$enddefinitions $end
#0
$dumpvars
0&
1%
1$
0#
0"
0!
$end
#5
0$
0%
1#
#10
1$
1%
0#
1"
#15
0$
0%
1#
#20
1$
1%
0#
0"
1!
#25
0$
0%
1#
#30
1$
1%
1&
0#
1"
#35
0%
1#
