LabWeek3/basic.v
module invert(input wire i, output wire o1);
	assign o1 = !i;
endmodule

module and2(input wire i0, i1, output wire o2);
	assign o2 = i0 & i1;
endmodule

module or2(input wire i0, i1, output wire o3);
	assign o3 = i0 | i1;
endmodule

module xor2(input wire i0, i1, output wire o4);
	assign o4 = i0 ^ i1;
endmodule

module nand2(input wire i0, i1, output wire o5);
	wire t;
	and2 and2_0 (i0, i1, t);
	invert invert_0 (t, o5);
endmodule

LabWeek3/fulladd.v
module fulladd(input wire a, b, cin, output wire sum, cout);
wire[4:0] t;

    xor2 x0(a, b, t[0]);
    xor2 x1(t[0], cin, sum);

    and2 a0(a, b, t[1]);
    and2 a1(a, cin, t[2]);
    and2 a2(b, cin, t[3]);
    
    or2 o0(t[1], t[2], t[4]);
    or2 o1(t[3], t[4], cout);
endmodule

LabWeek3/tb_fulladd.v
module fulladd_tb;
reg aa,bb,cc;
wire ss,cy;
fulladd add1(.a(aa), .b(bb), .cin(cc), .sum(ss), .cout(cy));

initial
begin
$dumpfile("fulladd_test.vcd");
$dumpvars(0, fulladd_tb);
end

initial
begin
$monitor($time, " a = %b, b = %b, c = %b, sum = %b, carry = %b", aa, bb, cc, ss, cy);
#0 aa = 1'b0; bb = 1'b0; cc=1'b0;
#5 aa = 1'b0; bb = 1'b0; cc=1'b1;
#5 aa = 1'b0; bb = 1'b1; cc=1'b0;
#5 aa = 1'b0; bb = 1'b1; cc=1'b1;
#5 aa = 1'b1; bb = 1'b0; cc=1'b0;
#5 aa = 1'b1; bb = 1'b0; cc=1'b1;
#5 aa = 1'b1; bb = 1'b1; cc=1'b0;
#5 aa = 1'b1; bb = 1'b1; cc=1'b1;
end

endmodule

LabWeek3/fulladd_test.vcd
$date
	Mon Aug 28 23:53:19 2023
$end
$version
	Icarus Verilog
$end
$timescale
	1s
$end
$scope module fulladd_tb $end
$var wire 1 ! cy $end
$var wire 1 " ss $end
$var reg 1 # aa $end
$var reg 1 $ bb $end
$var reg 1 % cc $end
$scope module add1 $end
$var wire 1 & a $end
$var wire 1 ' b $end
$var wire 1 ( cin $end
$var wire 1 ! cout $end
$var wire 1 " sum $end
$var wire 5 ) t [4:0] $end
$scope module x0 $end
$var wire 1 & i0 $end
$var wire 1 ' i1 $end
$var wire 1 * o4 $end
$upscope $end
$scope module x1 $end
$var wire 1 + i0 $end
$var wire 1 ( i1 $end
$var wire 1 " o4 $end
$upscope $end
$scope module a0 $end
$var wire 1 & i0 $end
$var wire 1 ' i1 $end
$var wire 1 , o2 $end
$upscope $end
$scope module a1 $end
$var wire 1 & i0 $end
$var wire 1 ( i1 $end
$var wire 1 - o2 $end
$upscope $end
$scope module a2 $end
$var wire 1 ' i0 $end
$var wire 1 ( i1 $end
$var wire 1 . o2 $end
$upscope $end
$scope module o0 $end
$var wire 1 / i0 $end
$var wire 1 0 i1 $end
$var wire 1 1 o3 $end
$upscope $end
$scope module o1 $end
$var wire 1 2 i0 $end
$var wire 1 3 i1 $end
$var wire 1 ! o3 $end
$upscope $end
$upscope $end
$upscope $end
$enddefinitions $end
#0
$dumpvars
03
02
01
00
0/
0.
0-
0,
0+
0*
b0 )
0(
0'
0&
0%
0$
0#
0"
0!
$end
#5
1"
1%
1(
#10
1+
1"
1*
b1 )
0%
0(
1$
1'
#15
1!
12
0"
1.
b1001 )
1%
1(
#20
0!
02
1"
0.
b1 )
0%
0(
0$
0'
1#
1&
#25
1!
13
11
10
0"
1-
b10101 )
1%
1(
#30
00
0+
1/
0"
0-
0*
1,
b10010 )
0%
0(
1$
1'
#35
10
12
1"
1-
1.
b11110 )
1%
1(
