LabWeek3/basic.v
module invert(input wire i, output wire o1);
	assign o1 = !i;
endmodule

module and2(input wire i0, i1, output wire o2);
	assign o2 = i0 & i1;
endmodule

module or2(input wire i0, i1, output wire o3);
	assign o3 = i0 | i1;
endmodule

module xor2(input wire i0, i1, output wire o4);
	assign o4 = i0 ^ i1;
endmodule

module nand2(input wire i0, i1, output wire o5);
	wire t;
	and2 and2_0 (i0, i1, t);
	invert invert_0 (t, o5);
endmodule

LabWeek3/fulladd.v
module fulladd(input wire a, b, cin, output wire sum, cout);
wire[4:0] t;

    xor2 x0(a, b, t[0]);
    xor2 x1(t[0], cin, sum);

    and2 a0(a, b, t[1]);
    and2 a1(a, cin, t[2]);
    and2 a2(b, cin, t[3]);
    
    or2 o0(t[1], t[2], t[4]);
    or2 o1(t[3], t[4], cout);
endmodule

LabWeek3/rca.v
module fulladdR (input wire [3:0] a, b, input wire cin, output wire [3:0] sum, output wire cout);
wire [2:0] c;

fulladd u0(a[0], b[0], cin, sum[0], c[0]);
fulladd u1(a[1], b[1], c[0], sum[1], c[1]); 
fulladd u2(a[2], b[2], c[1], sum[2], c[2]); 
fulladd u3(a[3], b[3], c[2], sum[3], cout);

endmodule

LabWeek3/tb_rca.v
`timescale 1 ns / 1 ns
`define TESTVECS 10

module tb;
reg clk, reset;
reg [3:0] i0, i1;
reg cin;
wire [3:0] o;
wire cout;
reg [8:0] test_vecs [0:(`TESTVECS-1)];
integer i;

initial
begin
$dumpfile("rca_test.vcd");
$dumpvars(0,tb);
end

initial
begin
reset = 1'b1; 
#12.5 reset = 1'b0; 
end 

initial 
clk = 1'b0; 
always #5 clk =~ clk;

initial 
begin
test_vecs[0] = 9'b000000000;
test_vecs[1] = 9'b000000001;
test_vecs[2] = 9'b000100010;
test_vecs[3] = 9'b000100011;
test_vecs[4] = 9'b001000100;
test_vecs[5] = 9'b001000101;
test_vecs[6] = 9'b101010110;
test_vecs[7] = 9'b101010111;
test_vecs[8] = 9'b111011110;
test_vecs[9] = 9'b111011111;
end

initial 
{i0, i1, cin, i} = 0;
fulladdR u0 (i0, i1, cin, o, cout);

initial 
begin #6
for(i=0;i<`TESTVECS;i=i+1)
begin #10 {i0, i1, cin}=test_vecs[i];
end #100 $finish; 
end

always@(i0 or i1 or cin)
$monitor("At time = %t, i0 = %b, i1 = %b, cin = %b, Sum = %b, Carry = %b", $time, i0, i1, cin, o, cout);

endmodule

LabWeek3/rca_test.vcd
$date
	Mon Aug 28 23:58:13 2023
$end
$version
	Icarus Verilog
$end
$timescale
	1ns
$end
$scope module tb $end
$var wire 1 ! cout $end
$var wire 4 " o [3:0] $end
$var reg 1 # cin $end
$var reg 1 $ clk $end
$var integer 32 % i [31:0] $end
$var reg 4 & i0 [3:0] $end
$var reg 4 ' i1 [3:0] $end
$var reg 1 ( reset $end
$scope module u0 $end
$var wire 4 ) a [3:0] $end
$var wire 4 * b [3:0] $end
$var wire 3 + c [2:0] $end
$var wire 1 , cin $end
$var wire 1 ! cout $end
$var wire 4 - sum [3:0] $end
$scope module u0 $end
$var wire 1 . a $end
$var wire 1 / b $end
$var wire 1 , cin $end
$var wire 1 0 cout $end
$var wire 1 1 sum $end
$var wire 5 2 t [4:0] $end
$scope module x0 $end
$var wire 1 . i0 $end
$var wire 1 / i1 $end
$var wire 1 3 o4 $end
$upscope $end
$scope module x1 $end
$var wire 1 4 i0 $end
$var wire 1 , i1 $end
$var wire 1 1 o4 $end
$upscope $end
$scope module a0 $end
$var wire 1 . i0 $end
$var wire 1 / i1 $end
$var wire 1 5 o2 $end
$upscope $end
$scope module a1 $end
$var wire 1 . i0 $end
$var wire 1 , i1 $end
$var wire 1 6 o2 $end
$upscope $end
$scope module a2 $end
$var wire 1 / i0 $end
$var wire 1 , i1 $end
$var wire 1 7 o2 $end
$upscope $end
$scope module o0 $end
$var wire 1 8 i0 $end
$var wire 1 9 i1 $end
$var wire 1 : o3 $end
$upscope $end
$scope module o1 $end
$var wire 1 ; i0 $end
$var wire 1 < i1 $end
$var wire 1 0 o3 $end
$upscope $end
$upscope $end
$scope module u1 $end
$var wire 1 = a $end
$var wire 1 > b $end
$var wire 1 ? cin $end
$var wire 1 @ cout $end
$var wire 1 A sum $end
$var wire 5 B t [4:0] $end
$scope module x0 $end
$var wire 1 = i0 $end
$var wire 1 > i1 $end
$var wire 1 C o4 $end
$upscope $end
$scope module x1 $end
$var wire 1 D i0 $end
$var wire 1 ? i1 $end
$var wire 1 A o4 $end
$upscope $end
$scope module a0 $end
$var wire 1 = i0 $end
$var wire 1 > i1 $end
$var wire 1 E o2 $end
$upscope $end
$scope module a1 $end
$var wire 1 = i0 $end
$var wire 1 ? i1 $end
$var wire 1 F o2 $end
$upscope $end
$scope module a2 $end
$var wire 1 > i0 $end
$var wire 1 ? i1 $end
$var wire 1 G o2 $end
$upscope $end
$scope module o0 $end
$var wire 1 H i0 $end
$var wire 1 I i1 $end
$var wire 1 J o3 $end
$upscope $end
$scope module o1 $end
$var wire 1 K i0 $end
$var wire 1 L i1 $end
$var wire 1 @ o3 $end
$upscope $end
$upscope $end
$scope module u2 $end
$var wire 1 M a $end
$var wire 1 N b $end
$var wire 1 O cin $end
$var wire 1 P cout $end
$var wire 1 Q sum $end
$var wire 5 R t [4:0] $end
$scope module x0 $end
$var wire 1 M i0 $end
$var wire 1 N i1 $end
$var wire 1 S o4 $end
$upscope $end
$scope module x1 $end
$var wire 1 T i0 $end
$var wire 1 O i1 $end
$var wire 1 Q o4 $end
$upscope $end
$scope module a0 $end
$var wire 1 M i0 $end
$var wire 1 N i1 $end
$var wire 1 U o2 $end
$upscope $end
$scope module a1 $end
$var wire 1 M i0 $end
$var wire 1 O i1 $end
$var wire 1 V o2 $end
$upscope $end
$scope module a2 $end
$var wire 1 N i0 $end
$var wire 1 O i1 $end
$var wire 1 W o2 $end
$upscope $end
$scope module o0 $end
$var wire 1 X i0 $end
$var wire 1 Y i1 $end
$var wire 1 Z o3 $end
$upscope $end
$scope module o1 $end
$var wire 1 [ i0 $end
$var wire 1 \ i1 $end
$var wire 1 P o3 $end
$upscope $end
$upscope $end
$scope module u3 $end
$var wire 1 ] a $end
$var wire 1 ^ b $end
$var wire 1 _ cin $end
$var wire 1 ! cout $end
$var wire 1 ` sum $end
$var wire 5 a t [4:0] $end
$scope module x0 $end
$var wire 1 ] i0 $end
$var wire 1 ^ i1 $end
$var wire 1 b o4 $end
$upscope $end
$scope module x1 $end
$var wire 1 c i0 $end
$var wire 1 _ i1 $end
$var wire 1 ` o4 $end
$upscope $end
$scope module a0 $end
$var wire 1 ] i0 $end
$var wire 1 ^ i1 $end
$var wire 1 d o2 $end
$upscope $end
$scope module a1 $end
$var wire 1 ] i0 $end
$var wire 1 _ i1 $end
$var wire 1 e o2 $end
$upscope $end
$scope module a2 $end
$var wire 1 ^ i0 $end
$var wire 1 _ i1 $end
$var wire 1 f o2 $end
$upscope $end
$scope module o0 $end
$var wire 1 g i0 $end
$var wire 1 h i1 $end
$var wire 1 i o3 $end
$upscope $end
$scope module o1 $end
$var wire 1 j i0 $end
$var wire 1 k i1 $end
$var wire 1 ! o3 $end
$upscope $end
$upscope $end
$upscope $end
$upscope $end
$enddefinitions $end
#0
$dumpvars
0k
0j
0i
0h
0g
0f
0e
0d
0c
0b
b0 a
0`
0_
0^
0]
0\
0[
0Z
0Y
0X
0W
0V
0U
0T
0S
b0 R
0Q
0P
0O
0N
0M
0L
0K
0J
0I
0H
0G
0F
0E
0D
0C
b0 B
0A
0@
0?
0>
0=
0<
0;
0:
09
08
07
06
05
04
03
b0 2
01
00
0/
0.
b0 -
0,
b0 +
b0 *
b0 )
1(
b0 '
b0 &
b0 %
0$
0#
b0 "
0!
$end
#5
1$
#10
0$
#13
0(
#15
1$
#16
b1 %
#20
0$
#25
1$
#26
11
b1 "
b1 -
b10 %
1#
1,
#30
0$
#35
1$
#36
1A
1?
10
b1 +
1<
1:
18
15
b10010 2
1.
1/
01
b10 "
b10 -
b11 %
b1 &
b1 )
b1 '
b1 *
0#
0,
#40
0$
#45
1$
#46
19
1;
11
b11 "
b11 -
16
17
b11110 2
b100 %
1#
1,
#50
0$
#55
1$
#56
0A
0?
00
1Q
0<
1L
1O
0:
1J
1@
b10 +
0I
08
1H
0K
0F
05
1E
0G
b10010 B
09
0;
0.
1=
0/
1>
01
b100 "
b100 -
06
07
b0 2
b101 %
b10 &
b10 )
b10 '
b10 *
0#
0,
#60
0$
#65
1$
#66
11
b101 "
b101 -
b110 %
1#
1,
#70
0$
#75
1$
#76
1!
1k
1i
14
1g
13
b1 2
1d
b10010 a
1]
1/
1^
11
b101 "
b101 -
b111 %
b1010 &
b1010 )
b1011 '
b1011 *
0#
0,
#80
0$
#85
1$
#86
1I
1K
1A
1F
1G
b11110 B
1?
10
b11 +
1;
01
b110 "
b110 -
17
b1001 2
b1000 %
1#
1,
#90
0$
#95
1$
#96
1h
1j
1`
1e
1f
b11110 a
0I
0K
1\
1_
0A
0F
0G
b10010 B
1Z
1P
0?
1Y
1X
1[
00
b110 +
1V
1U
1W
b11110 R
0;
1M
1N
11
b1101 "
b1101 -
07
b1 2
b1001 %
b1110 &
b1110 )
b1111 '
b1111 *
0#
0,
#100
0$
#105
1$
#106
1I
1K
1A
1F
1G
b11110 B
1?
10
b111 +
1;
01
b1110 "
b1110 -
17
b1001 2
b1010 %
1#
1,
